html_string_tools/__init__.py
html_string_tools/html_conversion.py
html_string_tools/html_string_tools.py
html_string_tools/tests/__init__.py
html_string_tools/tests/test_html.py
html_string_tools/tests/test_html_conversion.py
html_string_tools-0.4.2.dist-info/licenses/LICENSE
html_string_tools-0.4.2.dist-info/METADATA
html_string_tools-0.4.2.dist-info/WHEEL
html_string_tools-0.4.2.dist-info/entry_points.txt
html_string_tools-0.4.2.dist-info/top_level.txt
html_string_tools-0.4.2.dist-info/RECORD
