Metadata-Version: 2.4
Name: HTML-String-Tools
Version: 0.4.2
Summary: A simple set of scripts for handling, formatting, and converting HTML formatted text.
Home-page: https://github.com/Drakovek/HTML-String-Tools
Author: Drakovek
Author-email: DrakovekMail@gmail.com
Classifier: Programming Language :: Python :: 3
Classifier: License :: OSI Approved :: GNU General Public License v3 (GPLv3)
Classifier: Operating System :: OS Independent
Requires-Python: >=3.0
License-File: LICENSE
Dynamic: author
Dynamic: author-email
Dynamic: classifier
Dynamic: description
Dynamic: description-content-type
Dynamic: home-page
Dynamic: license-file
Dynamic: requires-python
Dynamic: summary
